pytpp/__init__.py
pytpp/__main__.py
pytpp/tpp_gui.py
pytpp/tpp_tools.py
pytpp/tpp_tools_regex.py
pytransit/DejaVuSans.ttf
pytransit/__init__.py
pytransit/__main__.py
pytransit/draw_trash.py
pytransit/fileDisplay.py
pytransit/file_system_py.py
pytransit/images.py
pytransit/norm_tools.py
pytransit/qcDisplay.py
pytransit/stat_tools.py
pytransit/tnseq_tools.py
pytransit/tnseq_tools_corrections.py
pytransit/transit_gui.py
pytransit/transit_tools.py
pytransit/trash.py
pytransit/view_trash.py
pytransit/analysis/CGI.py
pytransit/analysis/__init__.py
pytransit/analysis/anova.py
pytransit/analysis/base.py
pytransit/analysis/binomial.py
pytransit/analysis/corrplot.py
pytransit/analysis/essentiality.py
pytransit/analysis/example.py
pytransit/analysis/extract_GO_term_names.py
pytransit/analysis/extract_sanger.py
pytransit/analysis/gi.py
pytransit/analysis/griffin.py
pytransit/analysis/gumbel.py
pytransit/analysis/gumbel_mod.py
pytransit/analysis/gumbel_mod2.py
pytransit/analysis/gumbel_mod3.py
pytransit/analysis/gumbel_orig.py
pytransit/analysis/heatmap.py
pytransit/analysis/hmm.py
pytransit/analysis/norm.py
pytransit/analysis/normalize.py
pytransit/analysis/pathway_enrichment.py
pytransit/analysis/rankproduct.py
pytransit/analysis/resampling.py
pytransit/analysis/resampling_mod.py
pytransit/analysis/temp-gi.py
pytransit/analysis/temp.py
pytransit/analysis/temp1.py
pytransit/analysis/tn5gaps.py
pytransit/analysis/tnseq_stats.py
pytransit/analysis/ttnfitness.py
pytransit/analysis/utest.py
pytransit/analysis/zinb-interac.py
pytransit/analysis/zinb.py
pytransit/analysis/tmp/__init__.py
pytransit/analysis/tmp/anova.py
pytransit/analysis/tmp/base.py
pytransit/analysis/tmp/binomial.py
pytransit/analysis/tmp/corrplot.py
pytransit/analysis/tmp/essentiality.py
pytransit/analysis/tmp/example.py
pytransit/analysis/tmp/extract_GO_term_names.py
pytransit/analysis/tmp/extract_sanger.py
pytransit/analysis/tmp/gi.py
pytransit/analysis/tmp/griffin.py
pytransit/analysis/tmp/gumbel.py
tnseq_transit-3.3.10.post1.dist-info/LICENSE.md
tnseq_transit-3.3.10.post1.dist-info/METADATA
tnseq_transit-3.3.10.post1.dist-info/WHEEL
tnseq_transit-3.3.10.post1.dist-info/entry_points.txt
tnseq_transit-3.3.10.post1.dist-info/top_level.txt
tnseq_transit-3.3.10.post1.dist-info/RECORD
